foldercheck/__init__.py
foldercheck/command_line.py
foldercheck-1.2.2.dist-info/LICENSE
foldercheck-1.2.2.dist-info/METADATA
foldercheck-1.2.2.dist-info/WHEEL
foldercheck-1.2.2.dist-info/entry_points.txt
foldercheck-1.2.2.dist-info/top_level.txt
foldercheck-1.2.2.dist-info/RECORD
