Metadata-Version: 2.1
Name: foldercheck
Version: 1.2.2
Summary: Don't let your folders keep junk files! FolderCheck lets you review each file in the folder for you to decide wether you want to delete it or not!
Home-page: https://github.com/Animenosekai/python_folderchecker
Author: Anime no Sekai
Author-email: niichannomail@gmail.com
License: MIT
Download-URL: https://github.com/Animenosekai/python_folderchecker/archive/v1.2.1.tar.gz
Keywords: folder,check,review,file,management,organize
Platform: UNKNOWN
Classifier: Development Status :: 4 - Beta
Classifier: License :: OSI Approved :: MIT License
Classifier: Programming Language :: Python :: 3
Classifier: Programming Language :: Python :: 3.4
Classifier: Programming Language :: Python :: 3.5
Classifier: Programming Language :: Python :: 3.6
Classifier: Programming Language :: Python :: 3.7
Classifier: Programming Language :: Python :: 3.8
Requires-Dist: lifeeasy
